[{"name":"final list","link":"","items":[{"itemId":12815,"price":5000,"min":1,"max":1},{"itemId":12812,"price":8000,"min":1,"max":1},{"itemId":12502,"price":9000,"min":1,"max":1},{"itemId":12503,"price":12000,"min":1,"max":1},{"itemId":13037,"price":15000,"min":1,"max":1},{"itemId":16261,"price":10000,"min":1,"max":1},{"itemId":12916,"price":7800,"min":1,"max":1},{"itemId":12917,"price":3900,"min":1,"max":1},{"itemId":12434,"price":20000,"min":1,"max":1},{"itemId":12428,"price":12000,"min":1,"max":1},{"itemId":13036,"price":18000,"min":1,"max":1},{"itemId":13626,"price":24000,"min":1,"max":1},{"itemId":16260,"price":12000,"min":1,"max":1},{"itemId":22031,"price":4800,"min":1,"max":3},{"itemId":12436,"price":30000,"min":1,"max":1},{"itemId":13038,"price":35000,"min":1,"max":1},{"itemId":16262,"price":28000,"min":1,"max":1},{"itemId":22026,"price":2500,"min":1,"max":3},{"itemId":22027,"price":500,"min":1,"max":3},{"itemId":22028,"price":3000,"min":1,"max":3},{"itemId":22029,"price":500,"min":1,"max":3},{"itemId":22030,"price":3000,"min":1,"max":3},{"itemId":20124,"price":50000,"min":1,"max":1},{"itemId":12433,"price":20000,"min":1,"max":1},{"itemId":12810,"price":30000,"min":1,"max":1},{"itemId":13035,"price":50000,"min":1,"max":1},{"itemId":13625,"price":90000,"min":1,"max":1},{"itemId":16259,"price":15000,"min":1,"max":1},{"itemId":17143,"price":20000,"min":1,"max":1},{"itemId":17413,"price":30000,"min":1,"max":1},{"itemId":18055,"price":50000,"min":2,"max":2},{"itemId":12813,"price":15000,"min":1,"max":1},{"itemId":13307,"price":19000,"min":1,"max":1},{"itemId":13310,"price":16250,"min":1,"max":1},{"itemId":16301,"price":3300,"min":1,"max":1},{"itemId":15017,"price":1300,"min":1,"max":1},{"itemId":13040,"price":1990,"min":1,"max":1},{"itemId":22084,"price":420,"min":3,"max":5},{"itemId":22110,"price":1800,"min":3,"max":5},{"itemId":22081,"price":600,"min":3,"max":5},{"itemId":22016,"price":1500,"min":3,"max":5},{"itemId":22020,"price":560,"min":3,"max":5},{"itemId":22013,"price":3000,"min":3,"max":5},{"itemId":22032,"price":2000,"min":1,"max":1},{"itemId":22082,"price":6000,"min":1,"max":3},{"itemId":22109,"price":7300,"min":1,"max":3},{"itemId":12805,"price":20000,"min":1,"max":1},{"itemId":22258,"price":30000,"min":1,"max":3},{"itemId":22107,"price":3400,"min":1,"max":2},{"itemId":22014,"price":4000,"min":1,"max":3},{"itemId":22049,"price":10000,"min":1,"max":1},{"itemId":22052,"price":10000,"min":1,"max":1},{"itemId":22047,"price":10000,"min":1,"max":1},{"itemId":22048,"price":10000,"min":1,"max":1},{"itemId":22046,"price":10000,"min":1,"max":1},{"itemId":22051,"price":10000,"min":1,"max":1},{"itemId":22053,"price":5000,"min":1,"max":1},{"itemId":22041,"price":3000,"min":1,"max":1},{"itemId":22259,"price":30000,"min":1,"max":1},{"itemId":22260,"price":30000,"min":1,"max":1},{"itemId":22261,"price":30000,"min":1,"max":1},{"itemId":22262,"price":30000,"min":1,"max":1},{"itemId":22263,"price":30000,"min":1,"max":1},{"itemId":22264,"price":30000,"min":1,"max":1}]}]