[{"name":"JP 2010\/10\/15~2010\/10\/21","link":"https:\/\/w.atwiki.jp\/akaitsubasa-dq9\/pages\/207.html","items":[{"itemId":21393,"price":25800},{"itemId":20212,"price":24000},{"itemId":20816,"price":21250},{"itemId":19163,"price":21200},{"itemId":22035,"price":20000},{"itemId":19066,"price":18750},{"itemId":13607,"price":17000},{"itemId":21294,"price":15250},{"itemId":13208,"price":12250},{"itemId":13612,"price":11800},{"itemId":17394,"price":11000},{"itemId":22076,"price":10000},{"itemId":20017,"price":9250},{"itemId":13329,"price":9000},{"itemId":20206,"price":8250},{"itemId":20810,"price":8000},{"itemId":22082,"price":6000},{"itemId":22031,"price":4800},{"itemId":12808,"price":3600},{"itemId":18039,"price":3600},{"itemId":20408,"price":2350},{"itemId":22032,"price":2000},{"itemId":22114,"price":706},{"itemId":18002,"price":675},{"itemId":22144,"price":650},{"itemId":12801,"price":575},{"itemId":22084,"price":420},{"itemId":22025,"price":300},{"itemId":22142,"price":210},{"itemId":12414,"price":195}]},{"name":"JP 2010\/10\/8~2010\/10\/14","link":"https:\/\/w.atwiki.jp\/akaitsubasa-dq9\/pages\/207.html","items":[{"itemId":12802,"price":29000},{"itemId":21393,"price":25800},{"itemId":20400,"price":25000},{"itemId":12794,"price":8500},{"itemId":12812,"price":8000},{"itemId":12808,"price":7200},{"itemId":20410,"price":6200},{"itemId":12815,"price":5000},{"itemId":12811,"price":3600},{"itemId":22107,"price":3400},{"itemId":12807,"price":3200},{"itemId":22013,"price":3000},{"itemId":22110,"price":1800},{"itemId":12814,"price":1700},{"itemId":22016,"price":1500},{"itemId":12401,"price":1400},{"itemId":18018,"price":980},{"itemId":22081,"price":600},{"itemId":22020,"price":560},{"itemId":22084,"price":420}]},{"name":"JP 2010\/10\/1~2010\/10\/7","link":"https:\/\/w.atwiki.jp\/akaitsubasa-dq9\/pages\/207.html","items":[{"itemId":12424,"price":60000},{"itemId":12436,"price":30000},{"itemId":12810,"price":30000},{"itemId":12494,"price":25000},{"itemId":12426,"price":25000},{"itemId":12430,"price":25000},{"itemId":12781,"price":25000},{"itemId":12780,"price":25000},{"itemId":12432,"price":25000},{"itemId":12434,"price":20000},{"itemId":12433,"price":20000},{"itemId":12428,"price":12000},{"itemId":12493,"price":10000},{"itemId":12492,"price":10000},{"itemId":12491,"price":10000},{"itemId":12419,"price":9150},{"itemId":12499,"price":9100},{"itemId":12809,"price":9000},{"itemId":12480,"price":4300},{"itemId":12420,"price":1400}]},{"name":"JP 2010\/9\/24~2010\/9\/30","link":"https:\/\/w.atwiki.jp\/akaitsubasa-dq9\/pages\/207.html","items":[{"itemId":13621,"price":30000},{"itemId":13616,"price":30000},{"itemId":13515,"price":30000},{"itemId":21393,"price":25800},{"itemId":13209,"price":25000},{"itemId":12806,"price":25000},{"itemId":12907,"price":25000},{"itemId":12908,"price":25000},{"itemId":20414,"price":21500},{"itemId":20515,"price":17250},{"itemId":17176,"price":15000},{"itemId":15034,"price":15000},{"itemId":17177,"price":15000},{"itemId":15035,"price":15000},{"itemId":12412,"price":12400},{"itemId":12492,"price":10000},{"itemId":17091,"price":10000},{"itemId":15029,"price":10000},{"itemId":13291,"price":10000},{"itemId":21396,"price":8600},{"itemId":12295,"price":6250},{"itemId":18033,"price":2250},{"itemId":20406,"price":1575},{"itemId":17408,"price":110},{"itemId":19051,"price":100},{"itemId":19050,"price":7}]},{"name":"JP 2010\/9\/17~2010\/9\/23","link":"https:\/\/w.atwiki.jp\/akaitsubasa-dq9\/pages\/207.html","items":[{"itemId":19165,"price":40000},{"itemId":20915,"price":40000},{"itemId":20026,"price":40000},{"itemId":20716,"price":40000},{"itemId":20913,"price":33300},{"itemId":20024,"price":25000},{"itemId":20021,"price":22500},{"itemId":19163,"price":21200},{"itemId":20714,"price":18000},{"itemId":20911,"price":18000},{"itemId":19161,"price":17750},{"itemId":20015,"price":16800},{"itemId":19160,"price":12700},{"itemId":20712,"price":9750},{"itemId":20017,"price":9250},{"itemId":20904,"price":3950},{"itemId":22110,"price":1800},{"itemId":22016,"price":1500},{"itemId":22081,"price":600},{"itemId":22084,"price":420}]},{"name":"JP 2010\/9\/10~2009\/9\/16","link":"https:\/\/w.atwiki.jp\/akaitsubasa-dq9\/pages\/207.html","items":[{"itemId":20124,"price":50000},{"itemId":20213,"price":40000},{"itemId":20618,"price":40000},{"itemId":20120,"price":40000},{"itemId":20819,"price":40000},{"itemId":20818,"price":28000},{"itemId":20617,"price":25000},{"itemId":20119,"price":24500},{"itemId":20212,"price":24000},{"itemId":20118,"price":22500},{"itemId":20816,"price":21250},{"itemId":20615,"price":19900},{"itemId":20210,"price":18500},{"itemId":20815,"price":18250},{"itemId":20201,"price":9900},{"itemId":22110,"price":1800},{"itemId":22016,"price":1500},{"itemId":22081,"price":600},{"itemId":22020,"price":560},{"itemId":22084,"price":420}]},{"name":"JP 2010\/9\/3~2010\/9\/9","link":"https:\/\/w.atwiki.jp\/akaitsubasa-dq9\/pages\/207.html","items":[{"itemId":20412,"price":50000},{"itemId":20520,"price":40000},{"itemId":20318,"price":40000},{"itemId":19068,"price":40000},{"itemId":20415,"price":40000},{"itemId":19067,"price":24000},{"itemId":20517,"price":22500},{"itemId":20317,"price":22000},{"itemId":20414,"price":21500},{"itemId":20314,"price":20500},{"itemId":20516,"price":18000},{"itemId":20401,"price":17500},{"itemId":20515,"price":17250},{"itemId":19065,"price":15600},{"itemId":20311,"price":1980},{"itemId":22110,"price":1800},{"itemId":22016,"price":1500},{"itemId":22081,"price":600},{"itemId":22020,"price":560},{"itemId":22084,"price":420}]},{"name":"JP 2010\/8\/27~2010\/9\/2","link":"https:\/\/w.atwiki.jp\/akaitsubasa-dq9\/pages\/207.html","items":[{"itemId":17182,"price":30000},{"itemId":17413,"price":30000},{"itemId":17414,"price":30000},{"itemId":17143,"price":20000},{"itemId":17191,"price":15000},{"itemId":17163,"price":15000},{"itemId":17150,"price":15000},{"itemId":17168,"price":15000},{"itemId":17173,"price":15000},{"itemId":17194,"price":15000},{"itemId":17167,"price":15000},{"itemId":17152,"price":15000},{"itemId":17419,"price":15000},{"itemId":17165,"price":15000},{"itemId":17172,"price":15000},{"itemId":17160,"price":15000},{"itemId":17178,"price":15000},{"itemId":17176,"price":15000},{"itemId":17158,"price":15000},{"itemId":17177,"price":15000},{"itemId":17420,"price":15000},{"itemId":17164,"price":15000},{"itemId":17421,"price":15000},{"itemId":17179,"price":15000},{"itemId":17169,"price":15000},{"itemId":17166,"price":15000},{"itemId":17392,"price":15000},{"itemId":17170,"price":13500},{"itemId":17394,"price":11000},{"itemId":17142,"price":10000},{"itemId":17093,"price":10000},{"itemId":17091,"price":10000},{"itemId":17094,"price":10000},{"itemId":17096,"price":10000},{"itemId":17095,"price":10000},{"itemId":17192,"price":10000},{"itemId":17140,"price":10000},{"itemId":17141,"price":10000},{"itemId":17092,"price":10000},{"itemId":17193,"price":10000},{"itemId":17155,"price":5000}]},{"name":"JP 2010\/8\/20~2010\/8\/26","link":"https:\/\/w.atwiki.jp\/akaitsubasa-dq9\/pages\/207.html","items":[{"itemId":13026,"price":30000},{"itemId":13517,"price":30000},{"itemId":12912,"price":25000},{"itemId":12781,"price":25000},{"itemId":20816,"price":21250},{"itemId":16243,"price":20000},{"itemId":20401,"price":17500},{"itemId":15091,"price":15000},{"itemId":17163,"price":15000},{"itemId":17164,"price":15000},{"itemId":17093,"price":10000},{"itemId":12493,"price":10000},{"itemId":16290,"price":10000},{"itemId":13098,"price":10000},{"itemId":20310,"price":7000},{"itemId":12406,"price":6300},{"itemId":20410,"price":6200},{"itemId":21295,"price":3600},{"itemId":19058,"price":3500},{"itemId":18003,"price":2250},{"itemId":13504,"price":1250},{"itemId":18008,"price":1050},{"itemId":21002,"price":550},{"itemId":20300,"price":48}]}]